plesk/PleskPanel.py
plesk/__init__.py
plesk/utils.py
plesk/classes/Domain.py
plesk/classes/ServicePlans.py
plesk/classes/Subscription.py
plesk/classes/User.py
plesk/classes/__init__.py
plesk/definitions/Admin.py
plesk/definitions/CliCallRequest.py
plesk/definitions/CliCallResponse.py
plesk/definitions/Client.py
plesk/definitions/ClientRequest.py
plesk/definitions/ClientStatistics.py
plesk/definitions/ClientUpdateRequest.py
plesk/definitions/CreatedResponse.py
plesk/definitions/Database.py
plesk/definitions/DatabaseRequest.py
plesk/definitions/DatabaseServer.py
plesk/definitions/DatabaseUser.py
plesk/definitions/DatabaseUserRequest.py
plesk/definitions/DatabaseUserUpdateRequest.py
plesk/definitions/DnsRecord.py
plesk/definitions/DnsRecordRequest.py
plesk/definitions/DomainAlias.py
plesk/definitions/DomainReference.py
plesk/definitions/DomainRequest.py
plesk/definitions/DomainResponse.py
plesk/definitions/DomainStatus.py
plesk/definitions/ErrorResponse.py
plesk/definitions/Extension.py
plesk/definitions/ExtensionInstallRequest.py
plesk/definitions/FtpUser.py
plesk/definitions/FtpUserRequest.py
plesk/definitions/FtpUserUpdateRequest.py
plesk/definitions/OwnerClientReference.py
plesk/definitions/PlanReference.py
plesk/definitions/SecretKeyRequest.py
plesk/definitions/SecretKeyResponse.py
plesk/definitions/ServerIp.py
plesk/definitions/ServerLicense.py
plesk/definitions/ServerMeta.py
plesk/definitions/StatusResponse.py
plesk/definitions/__init__.py
plesk_api-0.0.1.dist-info/LICENSE
plesk_api-0.0.1.dist-info/METADATA
plesk_api-0.0.1.dist-info/WHEEL
plesk_api-0.0.1.dist-info/top_level.txt
plesk_api-0.0.1.dist-info/RECORD
