Metadata-Version: 2.1
Name: plesk-api
Version: 0.0.1
Summary: A simple API wrapper for Plesk
Home-page: https://www.github.com/reashetyrr/plesk-api
Author: Reashetyrr
Author-email: webmaster@reashetyr.software
License: MIT
Keywords: plesk
License-File: LICENSE
Requires-Dist: requests
